strip_notebook_metadata/__init__.py
strip_notebook_metadata/__main__.py
strip_notebook_metadata/main.py
strip_notebook_metadata-0.2.0.dist-info/LICENSE
strip_notebook_metadata-0.2.0.dist-info/METADATA
strip_notebook_metadata-0.2.0.dist-info/WHEEL
strip_notebook_metadata-0.2.0.dist-info/entry_points.txt
strip_notebook_metadata-0.2.0.dist-info/top_level.txt
strip_notebook_metadata-0.2.0.dist-info/RECORD
