Metadata-Version: 2.1
Name: strip-notebook-metadata
Version: 0.2.0
Summary: A package to strip metadata from code cells and markdowns without editing the output in Jupyter notebooks.
Home-page: https://github.com/kyriaki-mvr/strip-notebook-metadata
Author: Kyriaki Mavropoulou
Author-email: kyriaki@quanterra.gr
License: GPL
License-File: LICENSE
Requires-Dist: nbformat>=5.0.0
